{"type":"FeatureCollection","features":[{"type":"Feature","geometry":{"type":"Point","coordinates":[0.09231209568810073,49.492059483551486]},"properties":{"title":"Surfcasting","description":"pehce du bar","created_at":"2024-04-16T12:17:14.814Z"}}]}