{"type":"FeatureCollection","features":[{"type":"Feature","geometry":{"type":"Point","coordinates":[0.11583058293078352,49.505861300468666]},"properties":{"title":"restdyfguihojp","description":"jhgfuydsqdfghjkl","created_at":"2024-04-16T13:54:46.065Z"}}]}